evo_ingress/config.json
evo_ingress/evo-track.service
evo_ingress/install.sh
evo_ingress/src/exec-ingress.sh
evo_ingress/src/queue/hi.txt
evo_ingress/src/queue/hii.txt
evo_ingress/src/queue/hiis.txt
evo_ingress/src/tricks.yaml
evo_ingress/src/watch-directory.py
evo_ingress/tricks.yaml
evo_ingress-0.1.0.dist-info/WHEEL
evo_ingress-0.1.0.dist-info/METADATA
evo_ingress-0.1.0.dist-info/RECORD
