Metadata-Version: 2.1
Name: evo-ingress
Version: 0.1.0
Summary: 
Author: Moishe Keselman
Author-email: shimoshik@gmail.com
Requires-Python: >=3.7,<4.0
Classifier: Programming Language :: Python :: 3
Classifier: Programming Language :: Python :: 3.7
Classifier: Programming Language :: Python :: 3.8
Classifier: Programming Language :: Python :: 3.9
Requires-Dist: PyYAML (>=5.3.1,<6.0.0)
Requires-Dist: argh (>=0.26.2,<0.27.0)
Requires-Dist: watchdog (>=1.0.2,<2.0.0)
